devtools_cli/__init__.py
devtools_cli/commands/__init__.py
devtools_cli/commands/config/__init__.py
devtools_cli/commands/config/main.py
devtools_cli/commands/info/__init__.py
devtools_cli/commands/info/main.py
devtools_cli/commands/license/__init__.py
devtools_cli/commands/license/header.py
devtools_cli/commands/license/helpers.py
devtools_cli/commands/license/main.py
devtools_cli/commands/license/models.py
devtools_cli/commands/log/__init__.py
devtools_cli/commands/log/errors.py
devtools_cli/commands/log/helpers.py
devtools_cli/commands/log/main.py
devtools_cli/commands/log/models.py
devtools_cli/commands/version/__init__.py
devtools_cli/commands/version/descriptors.py
devtools_cli/commands/version/helpers.py
devtools_cli/commands/version/main.py
devtools_cli/commands/version/models.py
devtools_cli/main.py
devtools_cli/models.py
devtools_cli/utils.py
devtools_cli-0.14.1.dist-info/LICENSE
devtools_cli-0.14.1.dist-info/METADATA
devtools_cli-0.14.1.dist-info/WHEEL
devtools_cli-0.14.1.dist-info/entry_points.txt
devtools_cli-0.14.1.dist-info/RECORD
