Metadata-Version: 2.3
Name: devtools-cli
Version: 0.14.1
Summary: A toolbox of cross-language utility scripts for efficient software development.
License: MIT
Keywords: toolbox,cross-language,utility,scripts,software,development
Author: Mattias Aabmets
Author-email: mattias.aabmets@gmail.com
Requires-Python: >=3.10
Classifier: Development Status :: 5 - Production/Stable
Classifier: Environment :: Console
Classifier: Intended Audience :: Developers
Classifier: License :: OSI Approved :: MIT License
Classifier: Natural Language :: English
Classifier: Operating System :: OS Independent
Classifier: Programming Language :: Python :: 3
Classifier: Programming Language :: Python :: 3.10
Classifier: Programming Language :: Python :: 3.11
Classifier: Programming Language :: Python :: 3.12
Classifier: Programming Language :: Python :: 3.13
Classifier: Programming Language :: Python :: 3.8
Classifier: Programming Language :: Python :: 3.9
Classifier: Topic :: Software Development
Classifier: Topic :: Software Development :: Documentation
Classifier: Topic :: Software Development :: Libraries
Classifier: Topic :: Software Development :: Version Control
Classifier: Topic :: Utilities
Requires-Dist: httpx (>=0.25.0)
Requires-Dist: orjson (>=3.10.0)
Requires-Dist: pydantic (>=2.5.0)
Requires-Dist: pyyaml (>=6.0.0)
Requires-Dist: semver (>=3.0.0)
Requires-Dist: tomli (>=2.0.0) ; python_version < "3.11"
Requires-Dist: typer (>=0.10.0)
Project-URL: Repository, https://github.com/aabmets/devtools-cli
